pylab.py
matplotlib/__init__.py
matplotlib/_animation_data.py
matplotlib/_blocking_input.py
matplotlib/_cm.py
matplotlib/_cm_listed.py
matplotlib/_color_data.py
matplotlib/_constrained_layout.py
matplotlib/_enums.py
matplotlib/_internal_utils.py
matplotlib/_layoutgrid.py
matplotlib/_mathtext.py
matplotlib/_mathtext_data.py
matplotlib/_pylab_helpers.py
matplotlib/_text_helpers.py
matplotlib/_version.py
matplotlib/afm.py
matplotlib/animation.py
matplotlib/artist.py
matplotlib/axis.py
matplotlib/backend_bases.py
matplotlib/backend_managers.py
matplotlib/backend_tools.py
matplotlib/bezier.py
matplotlib/blocking_input.py
matplotlib/category.py
matplotlib/cm.py
matplotlib/collections.py
matplotlib/colorbar.py
matplotlib/colors.py
matplotlib/container.py
matplotlib/contour.py
matplotlib/dates.py
matplotlib/docstring.py
matplotlib/dviread.py
matplotlib/figure.py
matplotlib/font_manager.py
matplotlib/fontconfig_pattern.py
matplotlib/gridspec.py
matplotlib/hatch.py
matplotlib/image.py
matplotlib/legend.py
matplotlib/legend_handler.py
matplotlib/lines.py
matplotlib/markers.py
matplotlib/mathtext.py
matplotlib/mia_func.py
matplotlib/mlab.py
matplotlib/offsetbox.py
matplotlib/patches.py
matplotlib/path.py
matplotlib/patheffects.py
matplotlib/pylab.py
matplotlib/pyplot.py
matplotlib/quiver.py
matplotlib/rcsetup.py
matplotlib/sankey.py
matplotlib/scale.py
matplotlib/spines.py
matplotlib/stackplot.py
matplotlib/streamplot.py
matplotlib/table.py
matplotlib/texmanager.py
matplotlib/text.py
matplotlib/textpath.py
matplotlib/ticker.py
matplotlib/tight_bbox.py
matplotlib/tight_layout.py
matplotlib/transforms.py
matplotlib/type1font.py
matplotlib/units.py
matplotlib/widgets.py
MIAvisual-0.0.6.dist-info/METADATA
MIAvisual-0.0.6.dist-info/WHEEL
MIAvisual-0.0.6.dist-info/top_level.txt
MIAvisual-0.0.6.dist-info/RECORD
