Metadata-Version: 2.1
Name: MIAvisual
Version: 0.0.6
Summary: OpenSourceProject
Author: BaeChangHyun
Author-email: matthew624@naver.com
License: MIT
Requires-Python: >=3
